[{"__type__":"cc.SpriteFrame","content":{"name":"待机-6-60003","texture":"29uEpLxXBKTqiXrxjlRa6V","rect":[234,158,74,114],"offset":[20,-7],"originalSize":[300,300],"rotated":1,"capInsets":[0,0,0,0]}},{"__type__":"cc.SpriteFrame","content":{"name":"行走-6-60001","texture":"29uEpLxXBKTqiXrxjlRa6V","rect":[230,470,66,108],"offset":[7,-4],"originalSize":[300,300],"rotated":1,"capInsets":[0,0,0,0]}},{"__type__":"cc.SpriteFrame","content":{"name":"行走-6-60003","texture":"29uEpLxXBKTqiXrxjlRa6V","rect":[2,550,56,108],"offset":[0,-1],"originalSize":[300,300],"rotated":1,"capInsets":[0,0,0,0]}},{"__type__":"cc.SpriteFrame","content":{"name":"死亡-6-60003","texture":"29uEpLxXBKTqiXrxjlRa6V","rect":[266,94,118,62],"offset":[-56,-40],"originalSize":[300,300],"capInsets":[0,0,0,0]}},{"__type__":"cc.SpriteFrame","content":{"name":"攻击-6-60002","texture":"29uEpLxXBKTqiXrxjlRa6V","rect":[142,2,134,86],"offset":[-43,-23],"originalSize":[300,300],"capInsets":[0,0,0,0]}},{"__type__":"cc.SpriteFrame","content":{"name":"行走-6-60004","texture":"29uEpLxXBKTqiXrxjlRa6V","rect":[114,506,64,108],"offset":[4,-4],"originalSize":[300,300],"rotated":1,"capInsets":[0,0,0,0]}},{"__type__":"cc.SpriteFrame","content":{"name":"待机-6-60000","texture":"29uEpLxXBKTqiXrxjlRa6V","rect":[2,332,70,114],"offset":[18,-7],"originalSize":[300,300],"rotated":1,"capInsets":[0,0,0,0]}},{"__type__":"cc.SpriteFrame","content":{"name":"技能-6-60005","texture":"29uEpLxXBKTqiXrxjlRa6V","rect":[386,138,114,112],"offset":[-12,-13],"originalSize":[300,300],"capInsets":[0,0,0,0]}},{"__type__":"cc.SpriteFrame","content":{"name":"施法-6-60000","texture":"29uEpLxXBKTqiXrxjlRa6V","rect":[2,176,80,114],"offset":[16,-7],"originalSize":[300,300],"rotated":1,"capInsets":[0,0,0,0]}},{"__type__":"cc.SpriteFrame","content":{"name":"技能-6-60000","texture":"29uEpLxXBKTqiXrxjlRa6V","rect":[232,394,74,112],"offset":[15,-9],"originalSize":[300,300],"rotated":1,"capInsets":[0,0,0,0]}},{"__type__":"cc.SpriteFrame","content":{"name":"施法-6-60002","texture":"29uEpLxXBKTqiXrxjlRa6V","rect":[118,362,84,112],"offset":[17,-8],"originalSize":[300,300],"rotated":1,"capInsets":[0,0,0,0]}},{"__type__":"cc.SpriteFrame","content":{"name":"待机-6-60002","texture":"29uEpLxXBKTqiXrxjlRa6V","rect":[118,214,74,114],"offset":[20,-7],"originalSize":[300,300],"rotated":1,"capInsets":[0,0,0,0]}},{"__type__":"cc.SpriteFrame","content":{"name":"行走-6-60006","texture":"29uEpLxXBKTqiXrxjlRa6V","rect":[346,466,62,110],"offset":[1,-4],"originalSize":[300,300],"rotated":1,"capInsets":[0,0,0,0]}},{"__type__":"cc.SpriteFrame","content":{"name":"攻击-6-60001","texture":"29uEpLxXBKTqiXrxjlRa6V","rect":[224,538,72,100],"offset":[9,-2],"originalSize":[300,300],"rotated":1,"capInsets":[0,0,0,0]}},{"__type__":"cc.SpriteFrame","content":{"name":"技能-6-60004","texture":"29uEpLxXBKTqiXrxjlRa6V","rect":[2,258,72,114],"offset":[-19,-12],"originalSize":[300,300],"rotated":1,"capInsets":[0,0,0,0]}},{"__type__":"cc.SpriteFrame","content":{"name":"技能-6-60003","texture":"29uEpLxXBKTqiXrxjlRa6V","rect":[350,252,68,114],"offset":[1,-6],"originalSize":[300,300],"rotated":1,"capInsets":[0,0,0,0]}},{"__type__":"cc.SpriteFrame","content":{"name":"死亡-6-60005","texture":"29uEpLxXBKTqiXrxjlRa6V","rect":[278,50,122,42],"offset":[-57,-45],"originalSize":[300,300],"capInsets":[0,0,0,0]}},{"__type__":"cc.SpriteFrame","content":{"name":"攻击-6-60004","texture":"29uEpLxXBKTqiXrxjlRa6V","rect":[2,404,76,112],"offset":[11,-8],"originalSize":[300,300],"rotated":1,"capInsets":[0,0,0,0]}},{"__type__":"cc.SpriteFrame","content":{"name":"死亡-6-60001","texture":"29uEpLxXBKTqiXrxjlRa6V","rect":[2,482,66,110],"offset":[-21,-17],"originalSize":[300,300],"rotated":1,"capInsets":[0,0,0,0]}},{"__type__":"cc.SpriteFrame","content":{"name":"技能-6-60002","texture":"29uEpLxXBKTqiXrxjlRa6V","rect":[118,290,70,114],"offset":[-16,2],"originalSize":[300,300],"rotated":1,"capInsets":[0,0,0,0]}},{"__type__":"cc.SpriteAtlas","_name":"anim_甘宁.plist","_spriteFrames":{"待机-6-60000":{"__uuid__":"29iCvTwC1LE5Xs9nJtBVne"},"待机-6-60001":{"__uuid__":"acfclDp25Mhpj78OHoxu0v"},"待机-6-60002":{"__uuid__":"3dB6fjPuVLb7/zEKiHoU/S"},"待机-6-60003":{"__uuid__":"0drSUS+1RKxKwMs8JYaEHS"},"待机-6-60004":{"__uuid__":"f4WO+gwQhGR6C+KDxL+YQD"},"技能-6-60000":{"__uuid__":"37wcsU4LNE8Z75pEmwNNwR"},"技能-6-60001":{"__uuid__":"e32awQ9C9CRohmC8l+Zb9a"},"技能-6-60002":{"__uuid__":"70Qn+JJc9HBrNeYzai1rIj"},"技能-6-60003":{"__uuid__":"601Al1O4RNlpkAerVFb0fF"},"技能-6-60004":{"__uuid__":"563BT9g/NPI4wgmMehjTHm"},"技能-6-60005":{"__uuid__":"2cjnCNdP5NFbLqciXhoYcz"},"技能-6-60006":{"__uuid__":"dcAaO8Q0NFg406OZt/Git5"},"攻击-6-60000":{"__uuid__":"87YH9UihRBFoaIoD+420HG"},"攻击-6-60001":{"__uuid__":"52bpolLJZMG7Uh3gQ0Wvd+"},"攻击-6-60002":{"__uuid__":"24zo6SIn5GK5MFfKYYPjKT"},"攻击-6-60003":{"__uuid__":"e72MM0ak1JQrX2/O/crZx1"},"攻击-6-60004":{"__uuid__":"6cYFx1eIFAVqoDHCbez83H"},"施法-6-60000":{"__uuid__":"2eNWJrewNNt52XZovX4Kr/"},"施法-6-60001":{"__uuid__":"fb90Ar+fVLxrsjBpSBdhPb"},"施法-6-60002":{"__uuid__":"39sKAw6+RDaq+k2QcggbNe"},"施法-6-60003":{"__uuid__":"89xxa/NKVDcqBZhBizfzzW"},"施法-6-60004":{"__uuid__":"f0hZInfzxFfJZJfSC8cMqs"},"死亡-6-60000":{"__uuid__":"d07+HV4p1Hdoa/BIMUIkBT"},"死亡-6-60001":{"__uuid__":"6fI5PDAYlEiZr7uOfAburW"},"死亡-6-60002":{"__uuid__":"bb2vjVH8VObri4VuU5cB3G"},"死亡-6-60003":{"__uuid__":"1fmgpMPHdJhJ/3ON5Jw3Eb"},"死亡-6-60004":{"__uuid__":"ddbnt1l3FFKaM2LoWQbkWd"},"死亡-6-60005":{"__uuid__":"64flCGD0lKLq0/WgRymoNK"},"死亡-6-60006":{"__uuid__":"d2P57eshtHqIlirJELZl9x"},"死亡-6-60007":{"__uuid__":"d6+QPm4WtHWLnlQ5bRMYGU"},"死亡-6-60008":{"__uuid__":"eeWERSBVBEpI7lRBaG3MF2"},"行走-6-60000":{"__uuid__":"8b98ecMvxPnai40gHBZnwA"},"行走-6-60001":{"__uuid__":"11hsyDBqdHXaQl/7uvJIRF"},"行走-6-60002":{"__uuid__":"fbxlloqXVHc5fxmdNCNdjg"},"行走-6-60003":{"__uuid__":"1axzzLulhKw57PwWuSpgek"},"行走-6-60004":{"__uuid__":"283H7lR7BGl7eqXWz8IiKk"},"行走-6-60005":{"__uuid__":"b85EnfjJZBDp4rM1q0H0wn"},"行走-6-60006":{"__uuid__":"4dkeyI69lE7o3LYP9yLqqi"},"行走-6-60007":{"__uuid__":"90h/tVVcpOn7th284hqYBt"},"行走-6-60008":{"__uuid__":"a6f0GaDd1HbrOVrnS5MB5x"}}},{"__type__":"cc.SpriteFrame","content":{"name":"攻击-6-60000","texture":"29uEpLxXBKTqiXrxjlRa6V","rect":[348,322,76,112],"offset":[11,-8],"originalSize":[300,300],"rotated":1,"capInsets":[0,0,0,0]}},{"__type__":"cc.SpriteFrame","content":{"name":"施法-6-60003","texture":"29uEpLxXBKTqiXrxjlRa6V","rect":[234,308,84,112],"offset":[17,-8],"originalSize":[300,300],"rotated":1,"capInsets":[0,0,0,0]}},{"__type__":"cc.SpriteFrame","content":{"name":"行走-6-60000","texture":"29uEpLxXBKTqiXrxjlRa6V","rect":[346,400,64,110],"offset":[4,-4],"originalSize":[300,300],"rotated":1,"capInsets":[0,0,0,0]}},{"__type__":"cc.SpriteFrame","content":{"name":"行走-6-60007","texture":"29uEpLxXBKTqiXrxjlRa6V","rect":[116,448,56,112],"offset":[-1,-3],"originalSize":[300,300],"rotated":1,"capInsets":[0,0,0,0]}},{"__type__":"cc.SpriteFrame","content":{"name":"行走-6-60008","texture":"29uEpLxXBKTqiXrxjlRa6V","rect":[346,400,64,110],"offset":[4,-4],"originalSize":[300,300],"rotated":1,"capInsets":[0,0,0,0]}},{"__type__":"cc.SpriteFrame","content":{"name":"待机-6-60001","texture":"29uEpLxXBKTqiXrxjlRa6V","rect":[234,234,72,114],"offset":[19,-7],"originalSize":[300,300],"rotated":1,"capInsets":[0,0,0,0]}},{"__type__":"cc.SpriteFrame","content":{"name":"行走-6-60005","texture":"29uEpLxXBKTqiXrxjlRa6V","rect":[402,66,70,108],"offset":[5,-5],"originalSize":[300,300],"rotated":1,"capInsets":[0,0,0,0]}},{"__type__":"cc.SpriteFrame","content":{"name":"死亡-6-60002","texture":"29uEpLxXBKTqiXrxjlRa6V","rect":[112,572,86,86],"offset":[-41,-21],"originalSize":[300,300],"capInsets":[0,0,0,0]}},{"__type__":"cc.SpriteFrame","content":{"name":"死亡-6-60000","texture":"29uEpLxXBKTqiXrxjlRa6V","rect":[404,2,62,106],"offset":[11,-10],"originalSize":[300,300],"rotated":1,"capInsets":[0,0,0,0]}},{"__type__":"cc.SpriteFrame","content":{"name":"死亡-6-60006","texture":"29uEpLxXBKTqiXrxjlRa6V","rect":[278,2,124,46],"offset":[-56,-46],"originalSize":[300,300],"capInsets":[0,0,0,0]}},{"__type__":"cc.SpriteFrame","content":{"name":"死亡-6-60007","texture":"29uEpLxXBKTqiXrxjlRa6V","rect":[278,2,124,46],"offset":[-56,-46],"originalSize":[300,300],"capInsets":[0,0,0,0]}},{"__type__":"cc.SpriteFrame","content":{"name":"技能-6-60006","texture":"29uEpLxXBKTqiXrxjlRa6V","rect":[232,394,74,112],"offset":[15,-9],"originalSize":[300,300],"rotated":1,"capInsets":[0,0,0,0]}},{"__type__":"cc.SpriteFrame","content":{"name":"死亡-6-60004","texture":"29uEpLxXBKTqiXrxjlRa6V","rect":[142,90,122,40],"offset":[-60,-42],"originalSize":[300,300],"capInsets":[0,0,0,0]}},{"__type__":"cc.SpriteFrame","content":{"name":"技能-6-60001","texture":"29uEpLxXBKTqiXrxjlRa6V","rect":[2,608,70,82],"offset":[-1,-24],"originalSize":[300,300],"rotated":1,"capInsets":[0,0,0,0]}},{"__type__":"cc.SpriteFrame","content":{"name":"攻击-6-60003","texture":"29uEpLxXBKTqiXrxjlRa6V","rect":[2,2,138,88],"offset":[-49,-21],"originalSize":[300,300],"capInsets":[0,0,0,0]}},{"__type__":"cc.SpriteFrame","content":{"name":"死亡-6-60008","texture":"29uEpLxXBKTqiXrxjlRa6V","rect":[278,2,124,46],"offset":[-56,-46],"originalSize":[300,300],"capInsets":[0,0,0,0]}},{"__type__":"cc.SpriteFrame","content":{"name":"施法-6-60004","texture":"29uEpLxXBKTqiXrxjlRa6V","rect":[118,132,80,114],"offset":[16,-7],"originalSize":[300,300],"rotated":1,"capInsets":[0,0,0,0]}},{"__type__":"cc.SpriteFrame","content":{"name":"待机-6-60004","texture":"29uEpLxXBKTqiXrxjlRa6V","rect":[2,332,70,114],"offset":[18,-7],"originalSize":[300,300],"rotated":1,"capInsets":[0,0,0,0]}},{"__type__":"cc.SpriteFrame","content":{"name":"行走-6-60002","texture":"29uEpLxXBKTqiXrxjlRa6V","rect":[340,530,58,104],"offset":[3,0],"originalSize":[300,300],"rotated":1,"capInsets":[0,0,0,0]}},{"__type__":"cc.SpriteFrame","content":{"name":"施法-6-60001","texture":"29uEpLxXBKTqiXrxjlRa6V","rect":[2,92,82,114],"offset":[16,-7],"originalSize":[300,300],"rotated":1,"capInsets":[0,0,0,0]}}]