[{"__type__":"cc.SpriteFrame","content":{"name":"huogong_013","texture":"27AHoIo0NNh6XdFosWRcWr","rect":[84,169,342,284],"offset":[15,-71],"originalSize":[480,480],"capInsets":[0,0,0,0]}},{"__type__":"cc.SpriteFrame","content":{"name":"huogong_007","texture":"bbDJ8askJDeJIZCr91C4bb","rect":[70,46,379,408],"offset":[19.5,-10],"originalSize":[480,480],"capInsets":[0,0,0,0]}},{"__type__":"cc.SpriteFrame","content":{"name":"huogong_009","texture":"87yAqRPUVK0bKPtYQ/Wfr3","rect":[69,46,381,407],"offset":[19.5,-9.5],"originalSize":[480,480],"capInsets":[0,0,0,0]}},[{"__type__":"cc.Prefab","_name":"火攻","data":{"__id__":1}},{"__type__":"cc.Node","_name":"火攻","_children":[{"__id__":2}],"_components":[{"__type__":"cc.Animation","node":{"__id__":1},"_defaultClip":{"__uuid__":"b71WOakb5GfZXPtBGC1Viq"},"_clips":[{"__uuid__":"b71WOakb5GfZXPtBGC1Viq"}]}],"_prefab":{"__type__":"cc.PrefabInfo","root":{"__id__":1},"asset":{"__uuid__":"785bI06EJBtb313cggIZUt"},"fileId":"a0Ma7HpfZCUrmSFra9kdbR"},"_contentSize":{"__type__":"cc.Size","width":400,"height":400},"_scaleX":1,"_scaleY":1,"_scale":{"__type__":"cc.Vec3","x":1,"y":1,"z":1}},{"__type__":"cc.Node","_name":"huogong_001","_parent":{"__id__":1},"_components":[{"__type__":"cc.Sprite","node":{"__id__":2},"_spriteFrame":{"__uuid__":"87fuvtL/xLJ5mrR+EtcJMB"}}],"_prefab":{"__type__":"cc.PrefabInfo","root":{"__id__":1},"asset":{"__uuid__":"785bI06EJBtb313cggIZUt"},"fileId":"ceMBIENThG+J4tnQE7RXJm"},"_contentSize":{"__type__":"cc.Size","width":97,"height":165},"_scaleX":1,"_scaleY":1,"_scale":{"__type__":"cc.Vec3","x":1,"y":1,"z":1}}],{"__type__":"cc.SpriteFrame","content":{"name":"huogong_015","texture":"197A7I2/9E+IPdi8QDA7WR","rect":[175,208,153,245],"offset":[11.5,-90.5],"originalSize":[480,480],"capInsets":[0,0,0,0]}},{"__type__":"cc.SpriteFrame","content":{"name":"huogong_001","texture":"91zmXwHPZMrq7zpyRZfCjC","rect":[213,125,97,165],"offset":[21.5,32.5],"originalSize":[480,480],"capInsets":[0,0,0,0]}},{"__type__":"cc.AnimationClip","_name":"火攻","_duration":1.1833333333333333,"curveData":{"paths":{"huogong_001":{"comps":{"cc.Sprite":{"spriteFrame":[{"frame":0,"value":{"__uuid__":"87fuvtL/xLJ5mrR+EtcJMB"}},{"frame":0.16666666666666666,"value":{"__uuid__":"ccAQ17XvdFiZJAEJNm6ypu"}},{"frame":0.3333333333333333,"value":{"__uuid__":"e21Vas7WJDUrQGUB+k7jXO"}},{"frame":0.5,"value":{"__uuid__":"11LFTJO/FDC7P7+LZi3p0B"}},{"frame":0.6666666666666666,"value":{"__uuid__":"1ewwiaCeJMOLM06Qq+xeRQ"}},{"frame":0.8333333333333334,"value":{"__uuid__":"d7rCtYpXxC/p0NUeyjGx4U"}},{"frame":0.9833333333333333,"value":{"__uuid__":"09alkx5O1NqZWV/1zDA66f"}},{"frame":1.1666666666666667,"value":{"__uuid__":"7fOO1BXPNKaL+1pbQk0efX"}}]}}}}}},{"__type__":"cc.SpriteFrame","content":{"name":"huogong_003","texture":"c4rZi7o8VNgbvWK9/68UQS","rect":[77,112,363,326],"offset":[18.5,-35],"originalSize":[480,480],"capInsets":[0,0,0,0]}},{"__type__":"cc.SpriteFrame","content":{"name":"huogong_011","texture":"cbGTmDiGpML43JtoZeNv8z","rect":[70,46,377,408],"offset":[18.5,-10],"originalSize":[480,480],"capInsets":[0,0,0,0]}},{"__type__":"cc.SpriteFrame","content":{"name":"huogong_005","texture":"36fmiHkUBKWpcI6bG8XSzx","rect":[67,72,380,382],"offset":[17,-23],"originalSize":[480,480],"capInsets":[0,0,0,0]}}]